paradime_dbt_provider/__init__.py
paradime_dbt_provider/example_dags/bolt_dbt_schedule_run.py
paradime_dbt_provider/example_dags/bolt_run_custom_commands.py
paradime_dbt_provider/example_dags/user_management.py
paradime_dbt_provider/hooks/__init__.py
paradime_dbt_provider/hooks/paradime.py
paradime_dbt_provider/operators/__init__.py
paradime_dbt_provider/operators/paradime.py
paradime_dbt_provider/sensors/__init__.py
paradime_dbt_provider/sensors/paradime.py
airflow_provider_paradime_dbt-1.1.0.dist-info/LICENSE
airflow_provider_paradime_dbt-1.1.0.dist-info/METADATA
airflow_provider_paradime_dbt-1.1.0.dist-info/WHEEL
airflow_provider_paradime_dbt-1.1.0.dist-info/entry_points.txt
airflow_provider_paradime_dbt-1.1.0.dist-info/top_level.txt
airflow_provider_paradime_dbt-1.1.0.dist-info/RECORD
