Metadata-Version: 2.1
Name: airflow-provider-paradime-dbt
Version: 1.1.0
Summary: The Airflow provider for Paradime to run and manage dbt™ jobs in production. The provider enables interaction with Paradime’s Bolt scheduler and management APIs.
Author-email: Bhuvan Singla <bhuvan@paradime.io>
License: Apache License 2.0
Project-URL: Homepage, https://paradime.io
Project-URL: Source, https://github.com/paradime-io/airflow-provider-paradime-dbt
Classifier: Framework :: Apache Airflow
Classifier: Framework :: Apache Airflow :: Provider
Requires-Python: ~=3.8
License-File: LICENSE
Requires-Dist: apache-airflow>=2.4
Provides-Extra: dev
Requires-Dist: black==24.8.0; extra == "dev"
Requires-Dist: isort==5.13.2; extra == "dev"
Requires-Dist: mypy==1.14.1; extra == "dev"
Requires-Dist: types-requests>=2.31.0; extra == "dev"
